cefpanda/__init__.py
cefpanda/version.py
cefpanda-0.3.dist-info/LICENSE
cefpanda-0.3.dist-info/METADATA
cefpanda-0.3.dist-info/WHEEL
cefpanda-0.3.dist-info/top_level.txt
cefpanda-0.3.dist-info/RECORD
