Metadata-Version: 2.1
Name: cefpanda
Version: 0.3
Summary: A Panda3D-friendly wrapper around cefpython
Home-page: https://github.com/Moguri/cefpanda
Author: Mitchell Stokes
License: MIT
Keywords: panda3d gamedev
Platform: UNKNOWN
Classifier: Development Status :: 4 - Beta
Classifier: License :: OSI Approved :: MIT License
Classifier: Programming Language :: Python
Classifier: Programming Language :: Python :: 3
Classifier: Programming Language :: Python :: 3.6
Classifier: Programming Language :: Python :: 3.7
Requires-Dist: panda3d
Requires-Dist: cefpython3
